opthub_client_cli/__init__.py
opthub_client_cli/create.py
opthub_client_cli/delete.py
opthub_client_cli/mode.py
opthub_client_cli/opt.py
opthub_client_cli/read.py
opthub_client_cli/update.py
opthub_client_cli/util.py
opthub_client_cli-1.9.2.dist-info/LICENSE
opthub_client_cli-1.9.2.dist-info/METADATA
opthub_client_cli-1.9.2.dist-info/WHEEL
opthub_client_cli-1.9.2.dist-info/entry_points.txt
opthub_client_cli-1.9.2.dist-info/top_level.txt
opthub_client_cli-1.9.2.dist-info/RECORD
